textxjson/__init__.py
textxjson/json.py
textxjson/grammar/json.tx
textx_lang_json-0.0.dev3.dist-info/LICENSE
textx_lang_json-0.0.dev3.dist-info/METADATA
textx_lang_json-0.0.dev3.dist-info/WHEEL
textx_lang_json-0.0.dev3.dist-info/entry_points.txt
textx_lang_json-0.0.dev3.dist-info/top_level.txt
textx_lang_json-0.0.dev3.dist-info/RECORD
