Metadata-Version: 2.1
Name: textx-lang-json
Version: 0.0.dev3
Summary: A textX implementation of JSON.
Author-email: Jean-François Baget <baget@lirmm.fr>
License: MIT AND (Apache-2.0 OR BSD-2-clause)
Keywords: one,two
Classifier: Programming Language :: Python :: 3
Classifier: Operating System :: OS Independent
Requires-Python: >=3.7
License-File: LICENSE
Requires-Dist: textx
